imani/__init__.py
imani/flipflop_analysis.py
imani/hydration_analysis.py
imani/hydrationmembrane_analysis.py
imani/orientation_analysis.py
imani-0.1.2.dist-info/LICENSE
imani-0.1.2.dist-info/METADATA
imani-0.1.2.dist-info/WHEEL
imani-0.1.2.dist-info/entry_points.txt
imani-0.1.2.dist-info/top_level.txt
imani-0.1.2.dist-info/RECORD
