Metadata-Version: 2.1
Name: imani
Version: 0.1.2
Summary: Advanced molecular analysis tools for molecular dynamics simulations.
Home-page: https://github.com/melissajadem/imani
Author: Melissa Jade Mitchell
Classifier: Programming Language :: Python :: 3
Classifier: License :: OSI Approved :: MIT License
Classifier: Operating System :: OS Independent
Requires-Python: >=3.9
License-File: LICENSE
Requires-Dist: numpy
Requires-Dist: MDAnalysis
Requires-Dist: matplotlib
Requires-Dist: joblib
